mecoda_minka/__init__.py
mecoda_minka/data/taxon_tree.csv
mecoda_minka/mecoda_minka.py
mecoda_minka/models.py
mecoda_minka/py.typed
mecoda_minka/views.py
mecoda_minka-1.10.0.dist-info/LICENSE
mecoda_minka-1.10.0.dist-info/METADATA
mecoda_minka-1.10.0.dist-info/WHEEL
mecoda_minka-1.10.0.dist-info/RECORD
