Metadata-Version: 2.3
Name: mecoda-minka
Version: 1.10.0
Summary: High-performance library to download information using Minka API with optimized DataFrame processing.
License: GPL-3.0-or-later
Author: Ana Alvarez
Author-email: ana.alvarez@icm.csic.es
Requires-Python: >=3.9
Classifier: Development Status :: 4 - Beta
Classifier: Intended Audience :: Developers
Classifier: License :: OSI Approved :: GNU General Public License v3 or later (GPLv3+)
Classifier: Natural Language :: English
Classifier: Operating System :: POSIX
Classifier: Operating System :: Unix
Classifier: Programming Language :: Python
Classifier: Programming Language :: Python :: 3
Classifier: Programming Language :: Python :: 3.9
Classifier: Programming Language :: Python :: 3.10
Classifier: Programming Language :: Python :: 3.11
Classifier: Programming Language :: Python :: 3.12
Classifier: Programming Language :: Python :: 3.13
Classifier: Programming Language :: Python :: 3.7
Classifier: Programming Language :: Python :: 3.8
Classifier: Topic :: Utilities
Requires-Dist: folium
Requires-Dist: pandas
Requires-Dist: pydantic
Requires-Dist: requests
Project-URL: Repository, https://github.com/pynomaly/mecoda-minka
